[
  {
    "gid": 57031809,
    "name": "Домашняя школа",
    "members_count": 65
  },
  {
    "gid": 47465154,
    "name": "TOP PEOPLE MORDOR",
    "members_count": 8855
  },
  {
    "gid": 33410020,
    "name": "Газировка Dr Pepper в Нижнем Новгороде",
    "members_count": 89
  },
  {
    "gid": 56450854,
    "name": ".perversiō",
    "members_count": 6645
  },
  {
    "gid": 100063751,
    "name": "fp",
    "members_count": 1
  },
  {
    "gid": 75185191,
    "name": "Блог Jonn22 - Товарный бизнес и бизнес в сети",
    "members_count": 18122
  },
  {
    "gid": 66697672,
    "name": "sivard",
    "members_count": 452
  },
  {
    "gid": 41049802,
    "name": "Цитаты из лучших сериалов",
    "members_count": 5682
  },
  {
    "gid": 25447883,
    "name": "Леворадикал",
    "members_count": 11249
  },
  {
    "gid": 53023788,
    "name": "Математика - это проще, чем кажется",
    "members_count": 3131
  },
  {
    "gid": 32174764,
    "name": "Anton Maskeliade",
    "members_count": 1807
  },
  {
    "gid": 39595315,
    "name": "Тесак против Педофила \\ Оккупай-педофиляй 18+",
    "members_count": 89934
  },
  {
    "gid": 30624723,
    "name": "Let`s Vash",
    "members_count": 1664
  },
  {
    "gid": 43888243,
    "name": "Храбрейшие Воины | Bravest Warriors | BW Club",
    "members_count": 4125
  },
  {
    "gid": 23750039,
    "name": "liquid sound",
    "members_count": 8376
  },
  {
    "gid": 40251322,
    "name": "MW",
    "members_count": 8698
  },
  {
    "gid": 58135579,
    "name": "Нарушители ( Старая группа )",
    "members_count": 5071
  },
  {
    "gid": 37247932,
    "name": "My Little Penis",
    "members_count": 13610
  },
  {
    "gid": 64181021,
    "name": "РАЗДАРКИ (Вещи Даром!)",
    "members_count": 56
  }
]